execpp/__init__.py
execpp-0.0.2.dist-info/METADATA
execpp-0.0.2.dist-info/WHEEL
execpp-0.0.2.dist-info/top_level.txt
execpp-0.0.2.dist-info/zip-safe
execpp-0.0.2.dist-info/RECORD
