Metadata-Version: 2.1
Name: execpp
Version: 0.0.2
Summary: Exec cpp code
Home-page: 
Author: xjq
Author-email: xjq701229@outlook.com
License: UNKNOWN
Platform: UNKNOWN
Classifier: Programming Language :: Python :: 3
Requires-Dist: cppimport
Requires-Dist: robotpy-cppheaderparser
